[{"name": "Matthew Liberatore", "all_outings": [["9", 738941], ["15", 738941]], "past_days": []}, {"name": "Andrew Suarez", "all_outings": [["39", 738941]], "past_days": []}, {"name": "Drew VerHagen", "all_outings": [["12", 738941], ["9", 738941]], "past_days": [21, 21, 21]}, {"name": "Andre Pallante", "all_outings": [["16", 738941]], "past_days": [16, 16, 16]}, {"name": "Jacob Barnes", "all_outings": [["21", 738941]], "past_days": [21, 21, 21]}, {"name": "John King", "all_outings": [["11", 738941]], "past_days": [11, 11, 11]}, {"name": "Ryan Helsley", "all_outings": [["30", 738941]], "past_days": [30, 30, 30]}, {"name": "Casey Lawrence", "all_outings": [["21", 738941]], "past_days": [21, 21, 21]}]