[
  {
    "name": "Ryan Walker",
    "all_outings": [
      [
        "15",
        738986
      ],
      [
        "20",
        738988
      ],
      [
        "13",
        738991
      ],
      [
        "27",
        738992
      ]
    ],
    "past_days": [
      0,
      0,
      75
    ]
  },
  {
    "name": "Landen Roupp",
    "all_outings": [
      [
        "7",
        738986
      ],
      [
        "21",
        738988
      ]
    ],
    "past_days": [
      0,
      0,
      28
    ]
  },
  {
    "name": "Erik Miller",
    "all_outings": [
      [
        "16",
        738986
      ],
      [
        "20",
        738989
      ],
      [
        "15",
        738992
      ],
      [
        "14",
        738993
      ]
    ],
    "past_days": [
      0,
      14,
      65
    ]
  },
  {
    "name": "Nick Avila",
    "all_outings": [
      [
        "25",
        738989
      ],
      [
        "25",
        738992
      ]
    ],
    "past_days": [
      0,
      0,
      50
    ]
  },
  {
    "name": "Kai-Wei Teng",
    "all_outings": [
      [
        "39",
        738990
      ]
    ],
    "past_days": [
      0,
      0,
      39
    ]
  },
  {
    "name": "Taylor Rogers",
    "all_outings": [
      [
        "9",
        738990
      ],
      [
        "5",
        738992
      ]
    ],
    "past_days": [
      0,
      0,
      14
    ]
  },
  {
    "name": "Tyler Rogers",
    "all_outings": [
      [
        "10",
        738991
      ],
      [
        "13",
        738993
      ]
    ],
    "past_days": [
      0,
      13,
      23
    ]
  },
  {
    "name": "Camilo Doval",
    "all_outings": [
      [
        "27",
        738991
      ],
      [
        "13",
        738993
      ]
    ],
    "past_days": [
      0,
      13,
      40
    ]
  }
]